my_dataclass_is_a_dict/__init__.py
my_dataclass_is_a_dict/dict_mixin.py
my_dataclass_is_a_dict-0.2.dist-info/LICENSE
my_dataclass_is_a_dict-0.2.dist-info/METADATA
my_dataclass_is_a_dict-0.2.dist-info/WHEEL
my_dataclass_is_a_dict-0.2.dist-info/top_level.txt
my_dataclass_is_a_dict-0.2.dist-info/RECORD
