Metadata-Version: 2.1
Name: my-dataclass-is-a-dict
Version: 0.2
Summary: Give a dictionary interface to a dataclass
License: MIT License
Project-URL: homepage, https://github.com/dypabo/my-dataclass-is-a-dict
Project-URL: documentation, https://github.com/dypabo/my-dataclass-is-a-dict
Project-URL: repository, https://github.com/dypabo/my-dataclass-is-a-dict
License-File: LICENSE
Provides-Extra: dev
Requires-Dist: black (>=22.10.0) ; extra == 'dev'
Requires-Dist: flake8 (>=6.0.0) ; extra == 'dev'
Requires-Dist: mypy (>=0.991) ; extra == 'dev'
Requires-Dist: pylint (>=2.15.7) ; extra == 'dev'
Requires-Dist: pytest (>=7.2.0) ; extra == 'dev'
Requires-Dist: twine (>=4.0.2) ; extra == 'dev'
